{
    "route_id": "D1DF6BAF991E3CDC00134C28D27AEC12",
    "optimization_problem_id": "4EB3DAF007AC19628896BE4312A370F4",
    "user_route_rating": null,
    "member_id": 44143,
    "member_email": "demo@route4me.com",
    "member_first_name": "Administrator",
    "member_last_name": "Administrator",
    "member_picture": "http:\/\/www.gravatar.com\/avatar\/f9edaf83b05133a183ff07bf466b8c46?d=http%3A%2F%2Fwww.route4me.com%2Fstatic%2Fimg%2Favatar-placeholder.png&s=50",
    "member_tracking_subheadline": null,
    "approved_for_execution": false,
    "approved_revisions_counter": 0,
    "channel_name": "f8dceeb4b42538faf2ff95fc7b0924b5",
    "vehicle_alias": "N\/A",
    "driver_alias": "N\/A",
    "trip_distance": 2.34,
    "is_unrouted": false,
    "route_cost": 0,
    "route_revenue": 0,
    "net_revenue_per_distance_unit": 0,
    "created_timestamp": 1515547564,
    "mpg": 10,
    "gas_price": 2,
    "route_duration_sec": 317,
    "planned_total_route_duration": 25200,
    "actual_travel_distance": 0,
    "actual_travel_time": 0,
    "actual_footsteps": 0,
    "working_time": 0,
    "driving_time": 0,
    "idling_time": 0,
    "paying_miles": 0,
    "geofence_polygon_type": "circle",
    "geofence_polygon_size": 5,
    "destination_count": 1,
    "notes_count": 2,
    "parameters": {
        "is_upload": false,
        "rt": false,
        "route_name": "Tuesday 5th of June 2018 04:00:00 AM UTC (Part 002)",
        "route_date": 1528156800,
        "route_time": 25200,
        "shared_publicly": false,
        "disable_optimization": false,
        "optimize": "Distance",
        "lock_last": false,
        "vehicle_capacity": null,
        "vehicle_max_cargo_weight": null,
        "vehicle_max_cargo_volume": null,
        "vehicle_max_distance_mi": null,
        "subtour_max_revenue": null,
        "distance_unit": "mi",
        "travel_mode": "Driving",
        "avoid": "",
        "avoidance_zones": [],
        "vehicle_id": null,
        "driver_id": null,
        "dev_lat": null,
        "dev_lng": null,
        "route_max_duration": 28800,
        "route_email": null,
        "store_route": true,
        "metric": 3,
        "algorithm_type": 3,
        "member_id": 44143,
        "ip": 1276611531,
        "dm": 1,
        "dirm": 5,
        "parts": 10,
        "parts_min": 1,
        "device_id": null,
        "device_type": "web",
        "first_drive_then_wait_between_stops": false,
        "has_trailer": false,
        "trailer_weight_t": null,
        "limited_weight_t": null,
        "weight_per_axle_t": null,
        "truck_height": null,
        "truck_width": null,
        "truck_length": null,
        "truck_hazardous_goods": "",
        "optimization_quality": 0,
        "override_addresses": {},
        "max_tour_size": 2,
        "min_tour_size": 0,
        "uturn": 1,
        "leftturn": 1,
        "rightturn": 1,
        "route_time_multiplier": null,
        "route_service_time_multiplier": null
    },
    "addresses": [
        {
            "route_destination_id": 289863166,
            "alias": "",
            "member_id": 44143,
            "address": "King St & Flinders St, Melbourne VIC 3000, Australia",
            "is_depot": true,
            "timeframe_violation_state": null,
            "timeframe_violation_time": 0,
            "timeframe_violation_rate": 0,
            "lat": -37.8207115,
            "lng": 144.9581931,
            "curbside_lat": -37.8207115,
            "curbside_lng": 144.9581931,
            "priority": null,
            "route_id": null,
            "original_route_id": null,
            "route_name": null,
            "optimization_problem_id": "4EB3DAF007AC19628896BE4312A370F4",
            "sequence_no": 0,
            "geocoded": false,
            "preferred_geocoding": null,
            "failed_geocoding": false,
            "geocodings": [],
            "contact_id": null,
            "order_id": null,
            "address_stop_type": "DELIVERY",
            "is_visited": false,
            "timestamp_last_visited": null,
            "visited_lat": null,
            "visited_lng": null,
            "is_departed": false,
            "departed_lat": null,
            "departed_lng": null,
            "timestamp_last_departed": null,
            "group": null,
            "customer_po": null,
            "invoice_no": null,
            "reference_no": null,
            "order_no": null,
            "weight": 0,
            "cost": 0,
            "revenue": 0,
            "cube": 0,
            "pieces": 0,
            "first_name": null,
            "last_name": null,
            "email": null,
            "phone": null,
            "destination_note_count": 2,
            "drive_time_to_next_destination": 317,
            "abnormal_traffic_time_to_next_destination": null,
            "uncongested_time_to_next_destination": null,
            "traffic_time_to_next_destination": null,
            "distance_to_next_destination": 2.34,
            "channel_name": "42abdcc1831769d69bbb9dcbc78e07e3",
            "generated_time_window_start": 25200,
            "generated_time_window_end": 25200,
            "time_window_start": null,
            "time_window_end": null,
            "time_window_start_2": null,
            "time_window_end_2": null,
            "geofence_detected_visited_timestamp": null,
            "geofence_detected_departed_timestamp": null,
            "geofence_detected_service_time": null,
            "geofence_detected_visited_lat": null,
            "geofence_detected_visited_lng": null,
            "geofence_detected_departed_lat": null,
            "geofence_detected_departed_lng": null,
            "time": 0,
            "tracking_number": null,
            "custom_fields": {},
            "custom_fields_str_json": "{}",
            "custom_fields_config": null,
            "custom_fields_config_str_json": "null",
            "notes": [
                {
                    "note_id": 3237302,
                    "route_id": "D1DF6BAF991E3CDC00134C28D27AEC12",
                    "route_destination_id": 289863166,
                    "ts_added": 1517238859,
                    "activity_type": "dropoff",
                    "upload_id": "",
                    "upload_extension": null,
                    "upload_url": null,
                    "upload_type": null,
                    "contents": "test1111",
                    "lat": -37.820712,
                    "lng": 144.958193,
                    "device_type": "web",
                    "custom_types": [
                        {
                            "note_custom_entry_id": "ABCBA1228FA18968DBEECBFA2DA7899C850E15CA",
                            "note_id": "3237302",
                            "note_custom_type_id": "10",
                            "note_custom_value": "Backdoor",
                            "note_custom_type": "Dropoff Location"
                        },
                        {
                            "note_custom_entry_id": "0E297CA5584557C9C9782D74AEF476D33B06ACF1",
                            "note_id": "3237302",
                            "note_custom_type_id": "11",
                            "note_custom_value": "slippery",
                            "note_custom_type": "Conditions at Site"
                        }
                    ]
                },
                {
                    "note_id": 3237244,
                    "route_id": "D1DF6BAF991E3CDC00134C28D27AEC12",
                    "route_destination_id": 289863166,
                    "ts_added": 1517238163,
                    "activity_type": "dropoff",
                    "upload_id": "",
                    "upload_extension": null,
                    "upload_url": null,
                    "upload_type": null,
                    "contents": "test1111",
                    "lat": -37.820712,
                    "lng": 144.958193,
                    "device_type": "web",
                    "custom_types": [
                        {
                            "note_custom_entry_id": "2E98C4B9E5B1FC8010CAB87B96773140ADFD809B",
                            "note_id": "3237244",
                            "note_custom_type_id": "11",
                            "note_custom_value": "slippery",
                            "note_custom_type": "Conditions at Site"
                        }
                    ]
                }
            ],
            "wait_time_to_next_destination": 17683,
            "manifest": {
                "running_service_time": 0,
                "running_travel_time": 317,
                "running_wait_time": 17683,
                "running_distance": 2.34,
                "fuel_from_start": 0.234,
                "fuel_cost_from_start": 0.468,
                "estimated_arrival_time_ts": 1528182000,
                "estimated_departure_time_ts": 1528199683,
                "projected_arrival_time_ts": 1528182000,
                "projected_departure_time_ts": 1528199683,
                "actual_arrival_time_ts": null,
                "actual_departure_time_ts": null,
                "scheduled_arrival_time_ts": 1528182000,
                "scheduled_departure_time_ts": 1528182000,
                "time_impact": null
            }
        },
        {
            "route_destination_id": 289866641,
            "alias": "Arbory",
            "member_id": 44143,
            "address": "Flinders Walk, Melbourne VIC 3000, Australia",
            "is_depot": false,
            "timeframe_violation_state": null,
            "timeframe_violation_time": 0,
            "timeframe_violation_rate": 0,
            "lat": -37.819165,
            "lng": 144.965384,
            "curbside_lat": -37.819165,
            "curbside_lng": 144.965384,
            "priority": null,
            "route_id": "D1DF6BAF991E3CDC00134C28D27AEC12",
            "original_route_id": null,
            "optimization_problem_id": "4EB3DAF007AC19628896BE4312A370F4",
            "sequence_no": 1,
            "geocoded": false,
            "preferred_geocoding": null,
            "failed_geocoding": false,
            "geocodings": [],
            "contact_id": 24537266,
            "order_id": null,
            "address_stop_type": "DELIVERY",
            "is_visited": false,
            "timestamp_last_visited": null,
            "visited_lat": null,
            "visited_lng": null,
            "is_departed": false,
            "departed_lat": null,
            "departed_lng": null,
            "timestamp_last_departed": null,
            "group": null,
            "customer_po": null,
            "invoice_no": null,
            "reference_no": null,
            "order_no": null,
            "weight": 0,
            "cost": 0,
            "revenue": 0,
            "cube": 0,
            "pieces": 0,
            "first_name": null,
            "last_name": null,
            "email": null,
            "phone": null,
            "destination_note_count": 0,
            "drive_time_to_next_destination": null,
            "abnormal_traffic_time_to_next_destination": null,
            "uncongested_time_to_next_destination": null,
            "traffic_time_to_next_destination": null,
            "distance_to_next_destination": null,
            "channel_name": "4bcc60dcd9a04ed1a255bf25869c7eb1",
            "generated_time_window_start": 43200,
            "generated_time_window_end": 50400,
            "time_window_start": 43200,
            "time_window_end": 72000,
            "time_window_start_2": null,
            "time_window_end_2": null,
            "geofence_detected_visited_timestamp": null,
            "geofence_detected_departed_timestamp": null,
            "geofence_detected_service_time": null,
            "geofence_detected_visited_lat": null,
            "geofence_detected_visited_lng": null,
            "geofence_detected_departed_lat": null,
            "geofence_detected_departed_lng": null,
            "time": 7200,
            "tracking_number": "Z1PEMQ9X",
            "custom_fields": {
                "Has a Dog": "Beware of Dog",
                "Chlorine Gallons": "10"
            },
            "custom_fields_str_json": "{\"Has a Dog\":\"Beware of Dog\",\"Chlorine Gallons\":\"10\"}",
            "custom_fields_config": null,
            "custom_fields_config_str_json": "null",
            "notes": [],
            "wait_time_to_next_destination": null,
            "manifest": {
                "running_service_time": 7200,
                "running_travel_time": 582,
                "running_wait_time": 17683,
                "running_distance": 4.08,
                "fuel_from_start": 0.408,
                "fuel_cost_from_start": 0.816,
                "estimated_arrival_time_ts": 1528200000,
                "estimated_departure_time_ts": 1528207200,
                "projected_arrival_time_ts": 1528200000,
                "projected_departure_time_ts": 1528207200,
                "actual_arrival_time_ts": null,
                "actual_departure_time_ts": null,
                "scheduled_arrival_time_ts": 1528200317,
                "scheduled_departure_time_ts": 1528207517,
                "time_impact": null
            }
        }
    ],
    "links": {
        "route": "http:\/\/www.route4me.com\/api.v4\/route.php?route_id=D1DF6BAF991E3CDC00134C28D27AEC12&api_key=11111111111111111111111111111111&member_id=44143&device_tracking_history=0&original=0&notes=1",
        "optimization_problem_id": "http:\/\/www.route4me.com\/api.v4\/optimization_problem.php?optimization_problem_id=4EB3DAF007AC19628896BE4312A370F4&api_key=11111111111111111111111111111111&member_id=44143"
    },
    "notes": [
        {
            "note_id": 3237302,
            "route_id": "D1DF6BAF991E3CDC00134C28D27AEC12",
            "route_destination_id": 289863166,
            "ts_added": 1517238859,
            "activity_type": "dropoff",
            "upload_id": "",
            "upload_extension": null,
            "upload_url": null,
            "upload_type": null,
            "contents": "test1111",
            "lat": -37.820712,
            "lng": 144.958193,
            "device_type": "web",
            "custom_types": [
                {
                    "note_custom_entry_id": "ABCBA1228FA18968DBEECBFA2DA7899C850E15CA",
                    "note_id": "3237302",
                    "note_custom_type_id": "10",
                    "note_custom_value": "Backdoor",
                    "note_custom_type": "Dropoff Location"
                },
                {
                    "note_custom_entry_id": "0E297CA5584557C9C9782D74AEF476D33B06ACF1",
                    "note_id": "3237302",
                    "note_custom_type_id": "11",
                    "note_custom_value": "slippery",
                    "note_custom_type": "Conditions at Site"
                }
            ]
        },
        {
            "note_id": 3237244,
            "route_id": "D1DF6BAF991E3CDC00134C28D27AEC12",
            "route_destination_id": 289863166,
            "ts_added": 1517238163,
            "activity_type": "dropoff",
            "upload_id": "",
            "upload_extension": null,
            "upload_url": null,
            "upload_type": null,
            "contents": "test1111",
            "lat": -37.820712,
            "lng": 144.958193,
            "device_type": "web",
            "custom_types": [
                {
                    "note_custom_entry_id": "2E98C4B9E5B1FC8010CAB87B96773140ADFD809B",
                    "note_id": "3237244",
                    "note_custom_type_id": "11",
                    "note_custom_value": "slippery",
                    "note_custom_type": "Conditions at Site"
                }
            ]
        }
    ],
    "vehicle": null,
    "member_config_storage": {
        "destination_icon_width": "0",
        "MANDATORY_IMAGE_NOTE_FOR_MARK_STOP": "false",
        "voice_guided_navigation_enabled": "1",
        "sms_notifications_enabled": "0",
        "my_company_instagram_url": "my_company_instagram_url",
        "my_company_youtube_url": "my_company_youtube_url",
        "footer_any_questions": "footer_any_questions",
        "destination_icon_anchor": "0,1",
        "dynamic_inbound_gps_proximity_seconds": "49920",
        "display_destination_address": "0",
        "my_company_website_url": "my_company_website_url",
        "my_company_mailing_address": "my_company_mailing_address",
        "test_json": "{\n\"test\": \"test\"\n}",
        "my_company_fax_number": "my_company_fax_number",
        "my_company_email": "my_company_email",
        "my_company_twitter_url": "my_company_twitter_url",
        "earliest_email_notification_local_time": "58080",
        "MODULE__VOICE_NAVIGATION": "true",
        "email_notifications_enabled": "0",
        "email_preheader": "email_preheader",
        "my_company_facebook_url": "my_company_facebook_url",
        "MANDATORY_TEXT_NOTE_FOR_MARK_STOP": "false",
        "my_company_pinterest_url": "my_company_pinterest_url",
        "advance_notification_interval": "1",
        "hide_manifest_screen": "false",
        "call_notifications_enabled": "0",
        "my_company_phone_number": "my_company_phone_number",
        "MANDATORY_SIGNATURE_NOTE_FOR_MARK_STOP": "true",
        "HIDE_CUSTOM_NOTE_TYPE_DROPDOWN": "false",
        "notification_intro_message": "Hi {{first_name}}, your {{address_stop_type}} just got completed successfully."
    }
}